addletterboxcv/__init__.py
addletterboxcv-0.1.4.dist-info/LICENSE.txt
addletterboxcv-0.1.4.dist-info/METADATA
addletterboxcv-0.1.4.dist-info/WHEEL
addletterboxcv-0.1.4.dist-info/entry_points.txt
addletterboxcv-0.1.4.dist-info/top_level.txt
addletterboxcv-0.1.4.dist-info/RECORD
